client/__init__.py
client/achievement/__init__.py
client/achievement/watchmen_achievement_client.py
client/index.py
client/ml/__init__.py
client/ml/model/__init__.py
client/ml/model/factor_type.py
client/ml/model/notebook.py
client/ml/pd/__init__.py
client/ml/pd/untils.py
client/ml/unitls.py
client/sdk/__init__.py
client/sdk/watchmen/__init__.py
client/sdk/watchmen/sdk.py
watchmen_ml_python_sdk-0.1.20.dist-info/WHEEL
watchmen_ml_python_sdk-0.1.20.dist-info/METADATA
watchmen_ml_python_sdk-0.1.20.dist-info/RECORD
