Metadata-Version: 2.1
Name: watchmen-ml-python-sdk
Version: 0.1.20
Summary: 
Author: luke0623
Author-email: luke0623@outlook.com
Requires-Python: >=3.9,<4.0
Classifier: Programming Language :: Python :: 3
Classifier: Programming Language :: Python :: 3.9
Classifier: Programming Language :: Python :: 3.10
Requires-Dist: ipynbname (>=2021.3.2,<2022.0.0)
Requires-Dist: pandas (>=1.4.2,<2.0.0)
Requires-Dist: pydantic (>=1.9.1,<2.0.0)
Requires-Dist: requests (>=2.27.1,<3.0.0)
